sarif-schema.json
pylint2cso.py
pylint2sarif.py
pylint_sarif_unofficial-0.2.1.dist-info/LICENSE
pylint_sarif_unofficial-0.2.1.dist-info/METADATA
pylint_sarif_unofficial-0.2.1.dist-info/WHEEL
pylint_sarif_unofficial-0.2.1.dist-info/entry_points.txt
pylint_sarif_unofficial-0.2.1.dist-info/RECORD
