Metadata-Version: 2.1
Name: pylint-sarif-unofficial
Version: 0.2.1
Summary: Pylint output as SARIF
Home-page: https://github.com/EliahKagan/pylint-sarif
License: MIT
Keywords: pylint,sarif
Maintainer: Eliah Kagan
Maintainer-email: degeneracypressure@gmail.com
Requires-Python: >=3.7,<4.0
Classifier: Development Status :: 4 - Beta
Classifier: Intended Audience :: Developers
Classifier: License :: OSI Approved :: MIT License
Classifier: Programming Language :: Python :: 3
Classifier: Programming Language :: Python :: 3.7
Classifier: Programming Language :: Python :: 3.8
Classifier: Programming Language :: Python :: 3.9
Classifier: Programming Language :: Python :: 3.10
Classifier: Programming Language :: Python :: 3.11
Classifier: Topic :: Software Development
Classifier: Topic :: Software Development :: Quality Assurance
Requires-Dist: python-jsonschema-objects (>=0.4.4,<0.5.0)
Project-URL: Repository, https://github.com/EliahKagan/pylint-sarif
